vban_cmd/__init__.py
vban_cmd/bus.py
vban_cmd/command.py
vban_cmd/config.py
vban_cmd/error.py
vban_cmd/event.py
vban_cmd/factory.py
vban_cmd/iremote.py
vban_cmd/kinds.py
vban_cmd/macrobutton.py
vban_cmd/meta.py
vban_cmd/packet.py
vban_cmd/strip.py
vban_cmd/subject.py
vban_cmd/util.py
vban_cmd/vban.py
vban_cmd/vbancmd.py
vban_cmd/worker.py
vban_cmd-2.5.2.dist-info/LICENSE
vban_cmd-2.5.2.dist-info/METADATA
vban_cmd-2.5.2.dist-info/WHEEL
vban_cmd-2.5.2.dist-info/RECORD
